{
    "$schema": "https://schema.management.azure.com/schemas/2015-01-01/deploymentParameters.json#",
    "contentVersion": "1.0.0.0",
    "parameters": {
        "fileUris": {
            "value": "https://firewallstg.blob.core.windows.net/firewallcontainer/DisableWindowsFirewall.ps1?sp=r&st=2024-02-12T09:44:04Z&se=2024-05-12T09:44:04Z&sv=2022-11-02&sr=b&sig=O%2Bcnpfc9J5Ne1Ao1FCO0Nya0mhoxaGk18UQVwArb1Vo%3D"
        },
        "arguments": {
            "value": null
        },
        "vmName": {
            "value": "vm1"
        },
        "location": {
            "value": "uksouth"
        }
    }
}